skypulse/__init__.py
skypulse/__main__.py
skypulse/ai_weather.py
skypulse/cli.py
skypulse/client.py
skypulse/models.py
skypulse/notifications.py
skypulse/version.py
skypulse-1.1.0.dist-info/LICENSE.md
skypulse-1.1.0.dist-info/METADATA
skypulse-1.1.0.dist-info/WHEEL
skypulse-1.1.0.dist-info/entry_points.txt
skypulse-1.1.0.dist-info/top_level.txt
skypulse-1.1.0.dist-info/RECORD
