Metadata-Version: 2.1
Name: skypulse
Version: 1.1.0
Summary: Modern Python weather data retrieval library with async support and AI analysis
Home-page: https://github.com/HelpingAI/skypulse
Author: HelpingAI
Author-email: helpingai5@gmail.com
Project-URL: Bug Tracker, https://github.com/HelpingAI/skypulse/issues
Project-URL: Documentation, https://github.com/HelpingAI/skypulse#readme
Project-URL: Source, https://github.com/HelpingAI/skypulse
Project-URL: Changelog, https://github.com/HelpingAI/skypulse/blob/main/CHANGELOG.md
Keywords: weather,wttr.in,async,api,climate,forecast,meteorology,python,ai,artificial-intelligence,machine-learning,nlp,natural-language-processing,weather-analysis,weather-ai,weather-forecast,weather-data,weather-api,asyncio,real-time,openai,helpingai
Classifier: Development Status :: 5 - Production/Stable
Classifier: Intended Audience :: Developers
Classifier: License :: Other/Proprietary License
Classifier: Operating System :: OS Independent
Classifier: Programming Language :: Python :: 3
Classifier: Programming Language :: Python :: 3.7
Classifier: Programming Language :: Python :: 3.8
Classifier: Programming Language :: Python :: 3.9
Classifier: Programming Language :: Python :: 3.10
Classifier: Programming Language :: Python :: 3.11
Classifier: Topic :: Software Development :: Libraries :: Python Modules
Classifier: Topic :: Scientific/Engineering :: Atmospheric Science
Classifier: Topic :: Scientific/Engineering :: Artificial Intelligence
Classifier: Framework :: AsyncIO
Classifier: Natural Language :: English
Requires-Python: >=3.7
License-File: LICENSE.md
Requires-Dist: requests >=2.28.2
Requires-Dist: aiohttp >=3.8.4
Requires-Dist: pydantic >=2.0.0
Requires-Dist: typing-extensions >=4.5.0
Requires-Dist: python-dateutil >=2.8.2
Requires-Dist: openai >=1.3.0
Requires-Dist: rich >=13.3.5
Requires-Dist: typer >=0.9.0
Provides-Extra: dev
Requires-Dist: pytest >=7.0.0 ; extra == 'dev'
Requires-Dist: pytest-cov >=4.0.0 ; extra == 'dev'
Requires-Dist: pytest-asyncio >=0.20.0 ; extra == 'dev'
Requires-Dist: black >=22.0.0 ; extra == 'dev'
Requires-Dist: isort >=5.10.0 ; extra == 'dev'
Requires-Dist: mypy >=0.990 ; extra == 'dev'
Requires-Dist: ruff >=0.0.290 ; extra == 'dev'
Requires-Dist: pre-commit >=3.0.0 ; extra == 'dev'
Requires-Dist: build >=0.10.0 ; extra == 'dev'
Requires-Dist: twine >=4.0.0 ; extra == 'dev'
